tflowclient/__init__.py
tflowclient/cdp_flow.py
tflowclient/conf.py
tflowclient/demo_flow.py
tflowclient/flow.py
tflowclient/logs_gateway.py
tflowclient/observer.py
tflowclient/ui.py
tflowclient/entrypoints/__init__.py
tflowclient/entrypoints/cdp.py
tflowclient/entrypoints/demo.py
tflowclient/entrypoints/dumppalette.py
tflowview-0.6.0.dist-info/LICENSE-fr.txt
tflowview-0.6.0.dist-info/LICENSE.txt
tflowview-0.6.0.dist-info/METADATA
tflowview-0.6.0.dist-info/WHEEL
tflowview-0.6.0.dist-info/entry_points.txt
tflowview-0.6.0.dist-info/top_level.txt
tflowview-0.6.0.dist-info/RECORD
