Metadata-Version: 2.1
Name: tflowview
Version: 0.6.0
Summary: A text-based viewer for ECMWF workflow schedulers.
Author-email: Louis-François Meunier <louis-francois.meunier@meteo.fr>
License: CECILL-C
Project-URL: repository, https://github.com/UMR-CNRM/tflowclient
Keywords: SMS
Classifier: Development Status :: 4 - Beta
Classifier: Intended Audience :: Science/Research
Classifier: License :: CeCILL-C Free Software License Agreement (CECILL-C)
Requires-Python: >=3.7
License-File: LICENSE-fr.txt
License-File: LICENSE.txt
Requires-Dist: urwid
